pygremlinbox_osl_3_0/__init__.py
pygremlinbox_osl_3_0-1.4.0.dist-info/licenses/LICENCE
pygremlinbox_osl_3_0-1.4.0.dist-info/METADATA
pygremlinbox_osl_3_0-1.4.0.dist-info/WHEEL
pygremlinbox_osl_3_0-1.4.0.dist-info/top_level.txt
pygremlinbox_osl_3_0-1.4.0.dist-info/RECORD
