Metadata-Version: 2.4
Name: pygremlinbox-osl-3-0
Version: 1.4.0
Summary: PyGremlinBox OSL-3.0 - Supply chain security testing module with Open Software License v3.0
Author-email: Supply Chain Security Tester <simon@sigre.xyz>
Maintainer-email: Supply Chain Security Tester <simon@sigre.xyz>
License: OSL-3.0
Project-URL: Homepage, https://github.com/gocortexio/pygremlinbox
Project-URL: Repository, https://github.com/gocortexio/pygremlinbox.git
Project-URL: Issues, https://github.com/gocortexio/pygremlinbox/issues
Keywords: security,supply-chain,testing,osl,licence
Classifier: Development Status :: 4 - Beta
Classifier: Intended Audience :: Developers
Classifier: License :: OSI Approved :: Open Software License 3.0 (OSL-3.0)
Classifier: Operating System :: OS Independent
Classifier: Programming Language :: Python :: 3
Classifier: Programming Language :: Python :: 3.8
Classifier: Programming Language :: Python :: 3.9
Classifier: Programming Language :: Python :: 3.10
Classifier: Programming Language :: Python :: 3.11
Classifier: Programming Language :: Python :: 3.12
Classifier: Topic :: Security
Classifier: Topic :: Software Development :: Testing
Requires-Python: >=3.8
License-File: LICENCE
Dynamic: license-file
